algosec_resilient/__init__.py
algosec_resilient/components/__init__.py
algosec_resilient/components/algosec_base_component.py
algosec_resilient/components/algosec_check_host_internet_connectivity.py
algosec_resilient/components/algosec_client.py
algosec_resilient/components/algosec_isolate_host_from_network.py
algosec_resilient/components/algosec_list_associated_applications.py
algosec_resilient/util/__init__.py
algosec_resilient/util/config.py
algosec_resilient/util/customize.py
algosec_resilient/util/selftest.py
tests/__init__.py
tests/conftest.py
tests/test_algosec_check_host_internet_connectivity.py
tests/test_algosec_isolate_host_from_network.py
tests/test_algosec_list_associated_applications.py
algosec_resilient-1.3.0.dist-info/LICENSE
algosec_resilient-1.3.0.dist-info/METADATA
algosec_resilient-1.3.0.dist-info/WHEEL
algosec_resilient-1.3.0.dist-info/entry_points.txt
algosec_resilient-1.3.0.dist-info/top_level.txt
algosec_resilient-1.3.0.dist-info/RECORD
